bitagere/__init__.py
bitagere/cli/README.md
bitagere/cli/__init__.py
bitagere/cli/commands/__init__.py
bitagere/cli/commands/agere.py
bitagere/cli/commands/chain.py
bitagere/cli/commands/extrinsic.py
bitagere/cli/commands/helpers.py
bitagere/cli/commands/transfer.py
bitagere/cli/commands/wallet.py
bitagere/cli/main.py
bitagere/logging_config.py
bitagere/substrate/__init__.py
bitagere/substrate/interface.py
bitagere/utils/__init__.py
bitagere/utils/networking.py
bitagere/wallet/__init__.py
bitagere/wallet/keypair.py
bitagere/wallet/wallet.py
bitagere-0.0.9.dist-info/METADATA
bitagere-0.0.9.dist-info/WHEEL
bitagere-0.0.9.dist-info/entry_points.txt
bitagere-0.0.9.dist-info/licenses/LICENSE
bitagere-0.0.9.dist-info/RECORD
