Metadata-Version: 2.4
Name: bitagere
Version: 0.0.9
Summary: A BitAgere SDK with wallet and CLI tool.
License: MIT
License-File: LICENSE
Author: hacpy
Author-email: hacpy.lbx@gmail.com
Requires-Python: >=3.8,<4.0
Classifier: Development Status :: 3 - Alpha
Classifier: Intended Audience :: Developers
Classifier: License :: OSI Approved :: MIT License
Classifier: Programming Language :: Python :: 3
Classifier: Programming Language :: Python :: 3.8
Classifier: Programming Language :: Python :: 3.9
Classifier: Programming Language :: Python :: 3.10
Classifier: Programming Language :: Python :: 3.11
Classifier: Programming Language :: Python :: 3.12
Classifier: Programming Language :: Python :: 3.13
Classifier: Programming Language :: Python :: 3.14
Classifier: Topic :: Software Development :: Libraries :: Python Modules
Requires-Dist: click (>=7.0)
Requires-Dist: netaddr (>=0.8.0)
Requires-Dist: substrate-interface (>=0.9.23)
Requires-Dist: tenacity (>=8.0.0)
Project-URL: Repository, https://github.com/GEBcore/bitagere
